YubiOTP-1.0.0.post1.data/scripts/yubiclient
YubiOTP-1.0.0.post1.data/scripts/yubikey
yubiotp/__init__.py
yubiotp/client.py
yubiotp/crc.py
yubiotp/modhex.py
yubiotp/otp.py
yubiotp/test.py
YubiOTP-1.0.0.post1.dist-info/LICENSE
YubiOTP-1.0.0.post1.dist-info/METADATA
YubiOTP-1.0.0.post1.dist-info/WHEEL
YubiOTP-1.0.0.post1.dist-info/top_level.txt
YubiOTP-1.0.0.post1.dist-info/RECORD
