Metadata-Version: 2.1
Name: YubiOTP
Version: 1.0.0.post1
Summary: A library for verifying YubiKey OTP tokens, both locally and through a Yubico web service.
Home-page: https://github.com/django-otp/yubiotp
Author: Peter Sagerson
Author-email: psagers@ignorare.net
License: BSD
Project-URL: Documentation, https://yubiotp.readthedocs.io/
Project-URL: Source, https://github.com/django-otp/yubiotp
Platform: UNKNOWN
Classifier: Development Status :: 5 - Production/Stable
Classifier: Intended Audience :: Developers
Classifier: License :: OSI Approved :: BSD License
Classifier: Programming Language :: Python :: 3
Classifier: Programming Language :: Python :: 3 :: Only
Classifier: Topic :: Security
Classifier: Topic :: Software Development :: Libraries :: Python Modules
Requires-Dist: pycryptodome
